user_utils/__init__.py
user_utils/config.py
user_utils/crud.py
user_utils/database.py
user_utils/models.py
user_utils/schemas.py
user_utils/validators.py
userutilsvpetrov-0.1.1.dist-info/METADATA
userutilsvpetrov-0.1.1.dist-info/WHEEL
userutilsvpetrov-0.1.1.dist-info/top_level.txt
userutilsvpetrov-0.1.1.dist-info/RECORD
